lla/__init__.py
lla/interpreter.py
lla/parser.py
lla/tokenizer.py
lla/version.py
lla-0.0.6.dist-info/LICENSE.txt
lla-0.0.6.dist-info/METADATA
lla-0.0.6.dist-info/WHEEL
lla-0.0.6.dist-info/top_level.txt
lla-0.0.6.dist-info/RECORD
