Metadata-Version: 2.1
Name: lla
Version: 0.0.6
Summary: An interpreter for a basic logic language, inspired by two-element boolean algebra.
Home-page: https://github.com/duckinator/lla
Author: Ellen Marie Dash
Author-email: me@duckie.co
License: MIT
Platform: UNKNOWN
Classifier: Programming Language :: Python :: 3
Classifier: Programming Language :: Python :: 3.6
Classifier: Programming Language :: Python :: 3.7
Classifier: Programming Language :: Python :: 3.8
Classifier: License :: OSI Approved :: MIT License
Classifier: Operating System :: OS Independent
Requires-Python: >=3.6
Provides-Extra: testing
Requires-Dist: bork (==5.0.0) ; extra == 'testing'
Requires-Dist: pylint (==2.5.3) ; extra == 'testing'
Requires-Dist: pytest (==6.0.1) ; extra == 'testing'
Requires-Dist: pytest-pylint (==0.17.0) ; extra == 'testing'
Requires-Dist: pytest-mypy (==0.6.2) ; extra == 'testing'
